oztk/__init__.py
oztk/demo.py
oztk/oztk.py
oztk-0.0.1.dist-info/LICENSE
oztk-0.0.1.dist-info/METADATA
oztk-0.0.1.dist-info/WHEEL
oztk-0.0.1.dist-info/entry_points.txt
oztk-0.0.1.dist-info/top_level.txt
oztk-0.0.1.dist-info/RECORD
