Metadata-Version: 2.1
Name: oztk
Version: 0.0.1
Summary: Yuanzhen' s Python Toolkit Repo
Author-email: Yuanzhen Zhou <szrednick@gmail.com>
Project-URL: Homepage, https://github.com/zhouyuanzhen/oztk
Keywords: oztk,toolkit,utility,China
Classifier: Programming Language :: Python :: 3
Classifier: License :: OSI Approved :: MIT License
Classifier: Operating System :: OS Independent
Requires-Python: >=3.9
License-File: LICENSE
